kotlin version: 2.0.21
error message: org.jetbrains.kotlin.codegen.CompilationException: Back-end (JVM) Internal error: Couldn't transform method node:
collectAndRegister (ILjava/lang/String;Lkotlin/coroutines/Continuation;)Ljava/lang/Object;:
  @Lorg/jetbrains/annotations/Nullable;() // invisible
    // annotable parameter count: 3 (visible)
    // annotable parameter count: 3 (invisible)
    @Lorg/jetbrains/annotations/NotNull;() // invisible, parameter 1
    @Lorg/jetbrains/annotations/NotNull;() // invisible, parameter 2
   L0
    ALOAD 3
    INSTANCEOF com/example/lomanalyzer/vk/AuthorProfileCollector$collectAndRegister$1
    IFEQ L1
    ALOAD 3
    CHECKCAST com/example/lomanalyzer/vk/AuthorProfileCollector$collectAndRegister$1
    ASTORE 22
    ALOAD 22
    GETFIELD com/example/lomanalyzer/vk/AuthorProfileCollector$collectAndRegister$1.label : I
    LDC -2147483648
    IAND
    IFEQ L1
    ALOAD 22
    DUP
    GETFIELD com/example/lomanalyzer/vk/AuthorProfileCollector$collectAndRegister$1.label : I
    LDC -2147483648
    ISUB
    PUTFIELD com/example/lomanalyzer/vk/AuthorProfileCollector$collectAndRegister$1.label : I
    GOTO L2
   L1
    NEW com/example/lomanalyzer/vk/AuthorProfileCollector$collectAndRegister$1
    DUP
    ALOAD 0
    ALOAD 3
    INVOKESPECIAL com/example/lomanalyzer/vk/AuthorProfileCollector$collectAndRegister$1.<init> (Lcom/example/lomanalyzer/vk/AuthorProfileCollector;Lkotlin/coroutines/Continuation;)V
    ASTORE 22
   L2
    ALOAD 22
    GETFIELD com/example/lomanalyzer/vk/AuthorProfileCollector$collectAndRegister$1.result : Ljava/lang/Object;
    ASTORE 21
   L3
    INVOKESTATIC kotlin/coroutines/intrinsics/IntrinsicsKt.getCOROUTINE_SUSPENDED ()Ljava/lang/Object;
   L4
    LINENUMBER 59 L4
    ASTORE 23
    ALOAD 22
    GETFIELD com/example/lomanalyzer/vk/AuthorProfileCollector$collectAndRegister$1.label : I
    TABLESWITCH
      0: L5
      1: L6
      2: L7
      default: L8
   L5
    ALOAD 21
    INVOKESTATIC kotlin/ResultKt.throwOnFailure (Ljava/lang/Object;)V
   L9
   L10
    LINENUMBER 61 L10
    ALOAD 0
    GETFIELD com/example/lomanalyzer/vk/AuthorProfileCollector.postDao : Lcom/example/lomanalyzer/storage/dao/PostDao;
    ILOAD 1
    LDC "CURRENT"
    INVOKEVIRTUAL com/example/lomanalyzer/storage/dao/PostDao.findBySessionAndWindow (ILjava/lang/String;)Ljava/util/List;
    ASTORE 4
   L11
   L12
    LINENUMBER 62 L12
    ALOAD 4
    CHECKCAST java/lang/Iterable
    ASTORE 6
    NOP
   L13
    ICONST_0
    ISTORE 7
   L14
    LINENUMBER 158 L14
    ALOAD 6
    ASTORE 8
    NEW java/util/ArrayList
    DUP
    ALOAD 6
    BIPUSH 10
    INVOKESTATIC kotlin/collections/CollectionsKt.collectionSizeOrDefault (Ljava/lang/Iterable;I)I
    INVOKESPECIAL java/util/ArrayList.<init> (I)V
    CHECKCAST java/util/Collection
    ASTORE 9
   L15
    ICONST_0
    ISTORE 10
   L16
    LINENUMBER 159 L16
    ALOAD 8
    INVOKEINTERFACE java/lang/Iterable.iterator ()Ljava/util/Iterator; (itf)
    ASTORE 11
   L17
    ALOAD 11
    INVOKEINTERFACE java/util/Iterator.hasNext ()Z (itf)
    IFEQ L18
    ALOAD 11
    INVOKEINTERFACE java/util/Iterator.next ()Ljava/lang/Object; (itf)
    ASTORE 12
   L19
    LINENUMBER 160 L19
    ALOAD 9
    ALOAD 12
    CHECKCAST org/jetbrains/exposed/sql/ResultRow
    ASTORE 13
    ASTORE 19
   L20
    ICONST_0
    ISTORE 14
   L21
    LINENUMBER 62 L21
    ALOAD 13
    GETSTATIC com/example/lomanalyzer/storage/tables/Posts.INSTANCE : Lcom/example/lomanalyzer/storage/tables/Posts;
    INVOKEVIRTUAL com/example/lomanalyzer/storage/tables/Posts.getFromId ()Lorg/jetbrains/exposed/sql/Column;
    CHECKCAST org/jetbrains/exposed/sql/Expression
    INVOKEVIRTUAL org/jetbrains/exposed/sql/ResultRow.get (Lorg/jetbrains/exposed/sql/Expression;)Ljava/lang/Object;
    CHECKCAST java/lang/Number
    INVOKEVIRTUAL java/lang/Number.intValue ()I
    NOP
    GOTO L22
   L23
   L24
   L22
    INVOKESTATIC kotlin/coroutines/jvm/internal/Boxing.boxInt (I)Ljava/lang/Integer;
    ASTORE 20
    ALOAD 19
    ALOAD 20
   L25
    LINENUMBER 160 L25
    INVOKEINTERFACE java/util/Collection.add (Ljava/lang/Object;)Z (itf)
    POP
   L26
    GOTO L17
   L18
    LINENUMBER 161 L18
    ALOAD 9
   L27
    CHECKCAST java/util/List
   L28
    LINENUMBER 158 L28
    NOP
    GOTO L29
   L30
   L31
   L29
    CHECKCAST java/lang/Iterable
    ASTORE 6
   L32
    LINENUMBER 62 L32
    NOP
   L33
    ICONST_0
    ISTORE 7
   L34
    LINENUMBER 162 L34
    ALOAD 6
    ASTORE 8
    NEW java/util/ArrayList
    DUP
    INVOKESPECIAL java/util/ArrayList.<init> ()V
    CHECKCAST java/util/Collection
    ASTORE 9
   L35
    ICONST_0
    ISTORE 10
   L36
    LINENUMBER 163 L36
    ALOAD 8
    INVOKEINTERFACE java/lang/Iterable.iterator ()Ljava/util/Iterator; (itf)
    ASTORE 11
   L37
    ALOAD 11
    INVOKEINTERFACE java/util/Iterator.hasNext ()Z (itf)
    IFEQ L38
    ALOAD 11
    INVOKEINTERFACE java/util/Iterator.next ()Ljava/lang/Object; (itf)
    ASTORE 12
   L39
    ALOAD 12
    CHECKCAST java/lang/Number
    INVOKEVIRTUAL java/lang/Number.intValue ()I
    ISTORE 13
   L40
    ICONST_0
    ISTORE 14
   L41
    LINENUMBER 62 L41
    ILOAD 13
    ICONST_0
    IF_ICMPLE L42
    ICONST_1
    GOTO L43
   L42
    ICONST_0
   L43
    NOP
    GOTO L44
   L45
   L46
   L44
    INVOKESTATIC kotlin/coroutines/jvm/internal/Boxing.boxBoolean (Z)Ljava/lang/Boolean;
   L47
    LINENUMBER 163 L47
    CHECKCAST java/lang/Boolean
    INVOKEVIRTUAL java/lang/Boolean.booleanValue ()Z
    IFEQ L37
    ALOAD 9
    ALOAD 12
    INVOKEINTERFACE java/util/Collection.add (Ljava/lang/Object;)Z (itf)
    POP
   L48
    GOTO L37
   L38
    LINENUMBER 164 L38
    ALOAD 9
   L49
    CHECKCAST java/util/List
   L50
    LINENUMBER 162 L50
    NOP
    GOTO L51
   L52
   L53
   L51
    CHECKCAST java/lang/Iterable
   L54
    LINENUMBER 62 L54
    INVOKESTATIC kotlin/collections/CollectionsKt.distinct (Ljava/lang/Iterable;)Ljava/util/List;
    ASTORE 5
   L55
   L56
    LINENUMBER 64 L56
    ALOAD 5
    INVOKEINTERFACE java/util/List.isEmpty ()Z (itf)
    IFEQ L57
   L58
    LINENUMBER 65 L58
    ALOAD 0
    GETFIELD com/example/lomanalyzer/vk/AuthorProfileCollector.logger : Lcom/example/lomanalyzer/observability/Logger;
    ILOAD 1
    INVOKEDYNAMIC makeConcatWithConstants(I)Ljava/lang/String; [
      // handle kind 0x6 : INVOKESTATIC
      java/lang/invoke/StringConcatFactory.makeConcatWithConstants(Ljava/lang/invoke/MethodHandles$Lookup;Ljava/lang/String;Ljava/lang/invoke/MethodType;Ljava/lang/String;[Ljava/lang/Object;)Ljava/lang/invoke/CallSite;
      // arguments:
      "No authors found in CURRENT posts for session #\u0001"
    ]
    ACONST_NULL
    ICONST_2
    ACONST_NULL
    INVOKESTATIC com/example/lomanalyzer/observability/Logger.info$default (Lcom/example/lomanalyzer/observability/Logger;Ljava/lang/String;Ljava/util/Map;ILjava/lang/Object;)V
   L59
    LINENUMBER 66 L59
    ICONST_0
    INVOKESTATIC kotlin/coroutines/jvm/internal/Boxing.boxInt (I)Ljava/lang/Integer;
    ARETURN
   L60
   L57
   L61
   L62
    LINENUMBER 69 L62
    ALOAD 0
    GETFIELD com/example/lomanalyzer/vk/AuthorProfileCollector.sessionEventService : Lcom/example/lomanalyzer/vk/SessionEventService;
    ILOAD 1
    ALOAD 5
    INVOKEINTERFACE java/util/List.size ()I (itf)
    INVOKEDYNAMIC makeConcatWithConstants(I)Ljava/lang/String; [
      // handle kind 0x6 : INVOKESTATIC
      java/lang/invoke/StringConcatFactory.makeConcatWithConstants(Ljava/lang/invoke/MethodHandles$Lookup;Ljava/lang/String;Ljava/lang/invoke/MethodType;Ljava/lang/String;[Ljava/lang/Object;)Ljava/lang/invoke/CallSite;
      // arguments:
      "\u0420\u0435\u0435\u0441\u0442\u0440 \u0430\u0432\u0442\u043e\u0440\u043e\u0432: \u0001 \u0443\u043d\u0438\u043a\u0430\u043b\u044c\u043d\u044b\u0445 \u0430\u0432\u0442\u043e\u0440\u043e\u0432"
    ]
    ACONST_NULL
    ICONST_4
    ACONST_NULL
    INVOKESTATIC com/example/lomanalyzer/vk/SessionEventService.logInfo$default (Lcom/example/lomanalyzer/vk/SessionEventService;ILjava/lang/String;Ljava/lang/String;ILjava/lang/Object;)V
   L63
    LINENUMBER 72 L63
    ICONST_0
    ISTORE 6
   L64
   L65
    LINENUMBER 73 L65
    ICONST_0
    ISTORE 7
   L66
   L67
    LINENUMBER 74 L67
    ALOAD 5
    CHECKCAST java/lang/Iterable
    SIPUSH 200
    INVOKESTATIC kotlin/collections/CollectionsKt.chunked (Ljava/lang/Iterable;I)Ljava/util/List;
    ASTORE 8
   L68
   L69
    LINENUMBER 76 L69
    ALOAD 8
    CHECKCAST java/lang/Iterable
    INVOKEINTERFACE java/lang/Iterable.iterator ()Ljava/util/Iterator; (itf)
    ASTORE 9
   L70
    ICONST_0
    ISTORE 10
   L71
   L72
    ALOAD 9
    INVOKEINTERFACE java/util/Iterator.hasNext ()Z (itf)
    IFEQ L73
    ILOAD 10
    ISTORE 11
   L74
    ILOAD 10
    ICONST_1
    IADD
    ISTORE 10
    ALOAD 9
    INVOKEINTERFACE java/util/Iterator.next ()Ljava/lang/Object; (itf)
    CHECKCAST java/util/List
    ASTORE 12
   L75
   L76
    LINENUMBER 78 L76
    ALOAD 0
    GETFIELD com/example/lomanalyzer/vk/AuthorProfileCollector.apiClient : Lcom/example/lomanalyzer/vk/VkApiClient;
    ALOAD 12
    ALOAD 2
    ALOAD 22
    ALOAD 22
    ALOAD 0
    PUTFIELD com/example/lomanalyzer/vk/AuthorProfileCollector$collectAndRegister$1.L$0 : Ljava/lang/Object;
    ALOAD 22
    ALOAD 2
    PUTFIELD com/example/lomanalyzer/vk/AuthorProfileCollector$collectAndRegister$1.L$1 : Ljava/lang/Object;
    ALOAD 22
    ALOAD 5
    PUTFIELD com/example/lomanalyzer/vk/AuthorProfileCollector$collectAndRegister$1.L$2 : Ljava/lang/Object;
    ALOAD 22
    ALOAD 8
    PUTFIELD com/example/lomanalyzer/vk/AuthorProfileCollector$collectAndRegister$1.L$3 : Ljava/lang/Object;
    ALOAD 22
    ALOAD 9
    PUTFIELD com/example/lomanalyzer/vk/AuthorProfileCollector$collectAndRegister$1.L$4 : Ljava/lang/Object;
    ALOAD 22
    ILOAD 1
    PUTFIELD com/example/lomanalyzer/vk/AuthorProfileCollector$collectAndRegister$1.I$0 : I
    ALOAD 22
    ILOAD 6
    PUTFIELD com/example/lomanalyzer/vk/AuthorProfileCollector$collectAndRegister$1.I$1 : I
    ALOAD 22
    ILOAD 7
    PUTFIELD com/example/lomanalyzer/vk/AuthorProfileCollector$collectAndRegister$1.I$2 : I
    ALOAD 22
    ILOAD 10
    PUTFIELD com/example/lomanalyzer/vk/AuthorProfileCollector$collectAndRegister$1.I$3 : I
    ALOAD 22
    ILOAD 11
    PUTFIELD com/example/lomanalyzer/vk/AuthorProfileCollector$collectAndRegister$1.I$4 : I
    ALOAD 22
    ICONST_1
    PUTFIELD com/example/lomanalyzer/vk/AuthorProfileCollector$collectAndRegister$1.label : I
    INVOKEVIRTUAL com/example/lomanalyzer/vk/VkApiClient.usersGet (Ljava/util/List;Ljava/lang/String;Lkotlin/coroutines/Continuation;)Ljava/lang/Object;
   L77
    DUP
    ALOAD 23
    IF_ACMPNE L78
   L79
    LINENUMBER 59 L79
    ALOAD 23
    ARETURN
   L6
    ALOAD 22
    GETFIELD com/example/lomanalyzer/vk/AuthorProfileCollector$collectAndRegister$1.I$4 : I
    ISTORE 11
   L80
    ALOAD 22
    GETFIELD com/example/lomanalyzer/vk/AuthorProfileCollector$collectAndRegister$1.I$3 : I
    ISTORE 10
    ALOAD 22
    GETFIELD com/example/lomanalyzer/vk/AuthorProfileCollector$collectAndRegister$1.I$2 : I
    ISTORE 7
   L81
    ALOAD 22
    GETFIELD com/example/lomanalyzer/vk/AuthorProfileCollector$collectAndRegister$1.I$1 : I
    ISTORE 6
   L82
    ALOAD 22
    GETFIELD com/example/lomanalyzer/vk/AuthorProfileCollector$collectAndRegister$1.I$0 : I
    ISTORE 1
   L83
    ALOAD 22
    GETFIELD com/example/lomanalyzer/vk/AuthorProfileCollector$collectAndRegister$1.L$4 : Ljava/lang/Object;
    CHECKCAST java/util/Iterator
    ASTORE 9
    ALOAD 22
    GETFIELD com/example/lomanalyzer/vk/AuthorProfileCollector$collectAndRegister$1.L$3 : Ljava/lang/Object;
    CHECKCAST java/util/List
    ASTORE 8
   L84
    ALOAD 22
    GETFIELD com/example/lomanalyzer/vk/AuthorProfileCollector$collectAndRegister$1.L$2 : Ljava/lang/Object;
    CHECKCAST java/util/List
    ASTORE 5
   L85
    ALOAD 22
    GETFIELD com/example/lomanalyzer/vk/AuthorProfileCollector$collectAndRegister$1.L$1 : Ljava/lang/Object;
    CHECKCAST java/lang/String
    ASTORE 2
   L86
    ALOAD 22
    GETFIELD com/example/lomanalyzer/vk/AuthorProfileCollector$collectAndRegister$1.L$0 : Ljava/lang/Object;
    CHECKCAST com/example/lomanalyzer/vk/AuthorProfileCollector
    ASTORE 0
   L87
   L88
    NOP
    ALOAD 21
    INVOKESTATIC kotlin/ResultKt.throwOnFailure (Ljava/lang/Object;)V
    ALOAD 21
   L78
    CHECKCAST com/example/lomanalyzer/vk/models/VkResponse
    ASTORE 13
   L89
   L90
    LINENUMBER 80 L90
    ALOAD 13
    INVOKEVIRTUAL com/example/lomanalyzer/vk/models/VkResponse.getError ()Lcom/example/lomanalyzer/vk/models/VkError;
    IFNULL L91
   L92
    LINENUMBER 82 L92
    ALOAD 0
    GETFIELD com/example/lomanalyzer/vk/AuthorProfileCollector.sessionEventService : Lcom/example/lomanalyzer/vk/SessionEventService;
   L93
    LINENUMBER 83 L93
    ILOAD 1
    LDC "users.get"
    ALOAD 13
    INVOKEVIRTUAL com/example/lomanalyzer/vk/models/VkResponse.getError ()Lcom/example/lomanalyzer/vk/models/VkError;
    INVOKEVIRTUAL com/example/lomanalyzer/vk/models/VkError.getErrorCode ()I
    ALOAD 13
    INVOKEVIRTUAL com/example/lomanalyzer/vk/models/VkResponse.getError ()Lcom/example/lomanalyzer/vk/models/VkError;
    INVOKEVIRTUAL com/example/lomanalyzer/vk/models/VkError.getErrorMsg ()Ljava/lang/String;
   L94
    LINENUMBER 82 L94
    INVOKEVIRTUAL com/example/lomanalyzer/vk/SessionEventService.logApiError (ILjava/lang/String;ILjava/lang/String;)V
   L95
    LINENUMBER 85 L95
    NOP
    GOTO L72
   L96
   L91
   L97
   L98
    LINENUMBER 88 L98
    ALOAD 13
    INVOKEVIRTUAL com/example/lomanalyzer/vk/models/VkResponse.getResponse ()Ljava/lang/Object;
    CHECKCAST java/util/List
    ASTORE 15
   L99
    ALOAD 15
    IFNULL L100
    ALOAD 15
    GOTO L101
   L100
    NOP
    NOP
    GOTO L72
   L102
   L101
   L103
    ASTORE 14
   L104
   L105
    LINENUMBER 89 L105
    ALOAD 14
    INVOKEINTERFACE java/util/List.iterator ()Ljava/util/Iterator; (itf)
    ASTORE 15
   L106
   L107
    ALOAD 15
    INVOKEINTERFACE java/util/Iterator.hasNext ()Z (itf)
    IFEQ L108
    ALOAD 15
    INVOKEINTERFACE java/util/Iterator.next ()Ljava/lang/Object; (itf)
    CHECKCAST com/example/lomanalyzer/vk/models/VkUser
    ASTORE 16
   L109
   L110
    LINENUMBER 91 L110
    ALOAD 0
    GETFIELD com/example/lomanalyzer/vk/AuthorProfileCollector.authorDao : Lcom/example/lomanalyzer/storage/dao/AuthorDao;
    ALOAD 16
    INVOKEVIRTUAL com/example/lomanalyzer/vk/models/VkUser.getId ()I
    INVOKEVIRTUAL com/example/lomanalyzer/storage/dao/AuthorDao.findByVkId (I)Lorg/jetbrains/exposed/sql/ResultRow;
    ASTORE 17
   L111
   L112
    LINENUMBER 92 L112
    ALOAD 17
    IFNULL L113
   L114
    LINENUMBER 94 L114
    ALOAD 0
    GETFIELD com/example/lomanalyzer/vk/AuthorProfileCollector.authorDao : Lcom/example/lomanalyzer/storage/dao/AuthorDao;
    ALOAD 17
    GETSTATIC com/example/lomanalyzer/storage/tables/Authors.INSTANCE : Lcom/example/lomanalyzer/storage/tables/Authors;
    INVOKEVIRTUAL com/example/lomanalyzer/storage/tables/Authors.getId ()Lorg/jetbrains/exposed/sql/Column;
    CHECKCAST org/jetbrains/exposed/sql/Expression
    INVOKEVIRTUAL org/jetbrains/exposed/sql/ResultRow.get (Lorg/jetbrains/exposed/sql/Expression;)Ljava/lang/Object;
    CHECKCAST org/jetbrains/exposed/dao/id/EntityID
    INVOKEVIRTUAL org/jetbrains/exposed/dao/id/EntityID.getValue ()Ljava/lang/Object;
    CHECKCAST java/lang/Number
    INVOKEVIRTUAL java/lang/Number.intValue ()I
    ALOAD 16
    INVOKEDYNAMIC invoke(Lcom/example/lomanalyzer/vk/models/VkUser;)Lkotlin/jvm/functions/Function1; [
      // handle kind 0x6 : INVOKESTATIC
      java/lang/invoke/LambdaMetafactory.metafactory(Ljava/lang/invoke/MethodHandles$Lookup;Ljava/lang/String;Ljava/lang/invoke/MethodType;Ljava/lang/invoke/MethodType;Ljava/lang/invoke/MethodHandle;Ljava/lang/invoke/MethodType;)Ljava/lang/invoke/CallSite;
      // arguments:
      (Ljava/lang/Object;)Ljava/lang/Object;, 
      // handle kind 0x6 : INVOKESTATIC
      com/example/lomanalyzer/vk/AuthorProfileCollector.collectAndRegister$lambda$2(Lcom/example/lomanalyzer/vk/models/VkUser;Lorg/jetbrains/exposed/sql/statements/UpdateStatement;)Lkotlin/Unit;, 
      (Lorg/jetbrains/exposed/sql/statements/UpdateStatement;)Lkotlin/Unit;
    ]
    INVOKEVIRTUAL com/example/lomanalyzer/storage/dao/AuthorDao.update (ILkotlin/jvm/functions/Function1;)I
    POP
   L115
    LINENUMBER 101 L115
    ALOAD 17
    GETSTATIC com/example/lomanalyzer/storage/tables/Authors.INSTANCE : Lcom/example/lomanalyzer/storage/tables/Authors;
    INVOKEVIRTUAL com/example/lomanalyzer/storage/tables/Authors.getId ()Lorg/jetbrains/exposed/sql/Column;
    CHECKCAST org/jetbrains/exposed/sql/Expression
    INVOKEVIRTUAL org/jetbrains/exposed/sql/ResultRow.get (Lorg/jetbrains/exposed/sql/Expression;)Ljava/lang/Object;
    CHECKCAST org/jetbrains/exposed/dao/id/EntityID
    INVOKEVIRTUAL org/jetbrains/exposed/dao/id/EntityID.getValue ()Ljava/lang/Object;
    CHECKCAST java/lang/Number
    INVOKEVIRTUAL java/lang/Number.intValue ()I
    GOTO L116
   L113
   L117
    LINENUMBER 104 L117
    ALOAD 0
    GETFIELD com/example/lomanalyzer/vk/AuthorProfileCollector.authorDao : Lcom/example/lomanalyzer/storage/dao/AuthorDao;
   L118
    LINENUMBER 105 L118
    ALOAD 16
    INVOKEVIRTUAL com/example/lomanalyzer/vk/models/VkUser.getId ()I
   L119
    LINENUMBER 106 L119
    ALOAD 16
    INVOKEVIRTUAL com/example/lomanalyzer/vk/models/VkUser.getFirstName ()Ljava/lang/String;
   L120
    LINENUMBER 107 L120
    ALOAD 16
    INVOKEVIRTUAL com/example/lomanalyzer/vk/models/VkUser.getLastName ()Ljava/lang/String;
   L121
    LINENUMBER 108 L121
    ALOAD 16
    INVOKEVIRTUAL com/example/lomanalyzer/vk/models/VkUser.getScreenName ()Ljava/lang/String;
   L122
    LINENUMBER 109 L122
    ALOAD 16
    INVOKEVIRTUAL com/example/lomanalyzer/vk/models/VkUser.getFollowersCount ()Ljava/lang/Integer;
   L123
    LINENUMBER 110 L123
    ALOAD 16
    INVOKEVIRTUAL com/example/lomanalyzer/vk/models/VkUser.isClosed ()Z
   L124
    LINENUMBER 111 L124
    LDC "TOPIC_POST"
   L125
    LINENUMBER 104 L125
    INVOKEVIRTUAL com/example/lomanalyzer/storage/dao/AuthorDao.insert (ILjava/lang/String;Ljava/lang/String;Ljava/lang/String;Ljava/lang/Integer;ZLjava/lang/String;)I
   L116
   L126
    LINENUMBER 92 L126
    ISTORE 18
   L127
   L128
    LINENUMBER 116 L128
    ALOAD 0
    GETFIELD com/example/lomanalyzer/vk/AuthorProfileCollector.linkDao : Lcom/example/lomanalyzer/storage/dao/LinkDao;
    ILOAD 1
    ILOAD 18
    ACONST_NULL
    ICONST_4
    ACONST_NULL
    INVOKESTATIC com/example/lomanalyzer/storage/dao/LinkDao.linkSessionAuthor$default (Lcom/example/lomanalyzer/storage/dao/LinkDao;IILjava/lang/String;ILjava/lang/Object;)V
   L129
    LINENUMBER 117 L129
    ILOAD 6
    IINC 6 1
    POP
   L130
    LINENUMBER 120 L130
    ALOAD 16
    INVOKEVIRTUAL com/example/lomanalyzer/vk/models/VkUser.isClosed ()Z
    IFEQ L131
   L132
    LINENUMBER 121 L132
    ILOAD 7
    IINC 7 1
    POP
   L133
    LINENUMBER 122 L133
    ALOAD 0
    GETFIELD com/example/lomanalyzer/vk/AuthorProfileCollector.sessionEventService : Lcom/example/lomanalyzer/vk/SessionEventService;
    ILOAD 1
    ALOAD 16
    INVOKEVIRTUAL com/example/lomanalyzer/vk/models/VkUser.getId ()I
    INVOKEVIRTUAL com/example/lomanalyzer/vk/SessionEventService.logClosedAccount (II)V
   L131
   L134
   L135
   L136
    GOTO L107
   L108
   L137
   L138
    LINENUMBER 127 L138
    ILOAD 11
    ICONST_1
    IADD
    SIPUSH 200
    IMUL
    ALOAD 5
    INVOKEINTERFACE java/util/List.size ()I (itf)
    INVOKESTATIC kotlin/ranges/RangesKt.coerceAtMost (II)I
    ISTORE 15
   L139
   L140
    LINENUMBER 128 L140
    ALOAD 0
    GETFIELD com/example/lomanalyzer/vk/AuthorProfileCollector.progressReporter : Lcom/example/lomanalyzer/orchestration/ProgressReporter;
    NEW com/example/lomanalyzer/orchestration/ProgressEvent
    DUP
   L141
    LINENUMBER 129 L141
    ILOAD 15
    ALOAD 5
    INVOKEINTERFACE java/util/List.size ()I (itf)
    INVOKEDYNAMIC makeConcatWithConstants(II)Ljava/lang/String; [
      // handle kind 0x6 : INVOKESTATIC
      java/lang/invoke/StringConcatFactory.makeConcatWithConstants(Ljava/lang/invoke/MethodHandles$Lookup;Ljava/lang/String;Ljava/lang/invoke/MethodType;Ljava/lang/String;[Ljava/lang/Object;)Ljava/lang/invoke/CallSite;
      // arguments:
      "\u041f\u0440\u043e\u0444\u0438\u043b\u0438 \u0430\u0432\u0442\u043e\u0440\u043e\u0432: \u0001/\u0001"
    ]
   L142
    LINENUMBER 130 L142
    ILOAD 15
   L143
    LINENUMBER 131 L143
    ALOAD 5
    INVOKEINTERFACE java/util/List.size ()I (itf)
   L144
    LINENUMBER 128 L144
    ACONST_NULL
    ACONST_NULL
    NOP
    ICONST_0
    BIPUSH 56
    ACONST_NULL
    INVOKESPECIAL com/example/lomanalyzer/orchestration/ProgressEvent.<init> (Ljava/lang/String;IILjava/lang/Long;Ljava/lang/String;ZILkotlin/jvm/internal/DefaultConstructorMarker;)V
    INVOKEVIRTUAL com/example/lomanalyzer/orchestration/ProgressReporter.update (Lcom/example/lomanalyzer/orchestration/ProgressEvent;)V
   L145
    LINENUMBER 135 L145
    ALOAD 8
    INVOKEINTERFACE java/util/List.size ()I (itf)
    ICONST_5
    IF_ICMPLT L146
    ILOAD 11
    ICONST_1
    IADD
    ALOAD 8
    INVOKEINTERFACE java/util/List.size ()I (itf)
    ICONST_5
    IDIV
    ICONST_1
    INVOKESTATIC kotlin/ranges/RangesKt.coerceAtLeast (II)I
    IREM
    IFNE L146
   L147
    LINENUMBER 136 L147
    ALOAD 0
    GETFIELD com/example/lomanalyzer/vk/AuthorProfileCollector.sessionEventService : Lcom/example/lomanalyzer/vk/SessionEventService;
    ILOAD 1
    LDC "\u041f\u0440\u043e\u0444\u0438\u043b\u0438 \u0430\u0432\u0442\u043e\u0440\u043e\u0432"
    ILOAD 11
    ICONST_1
    IADD
    ALOAD 8
    INVOKEINTERFACE java/util/List.size ()I (itf)
    INVOKEVIRTUAL com/example/lomanalyzer/vk/SessionEventService.logProgress (ILjava/lang/String;II)V
   L146
   L148
   L149
    LINENUMBER 139 L149
    LDC 350
    ALOAD 22
    ALOAD 22
    ALOAD 0
    PUTFIELD com/example/lomanalyzer/vk/AuthorProfileCollector$collectAndRegister$1.L$0 : Ljava/lang/Object;
    ALOAD 22
    ALOAD 2
    PUTFIELD com/example/lomanalyzer/vk/AuthorProfileCollector$collectAndRegister$1.L$1 : Ljava/lang/Object;
    ALOAD 22
    ALOAD 5
    PUTFIELD com/example/lomanalyzer/vk/AuthorProfileCollector$collectAndRegister$1.L$2 : Ljava/lang/Object;
    ALOAD 22
    ALOAD 8
    PUTFIELD com/example/lomanalyzer/vk/AuthorProfileCollector$collectAndRegister$1.L$3 : Ljava/lang/Object;
    ALOAD 22
    ALOAD 9
    PUTFIELD com/example/lomanalyzer/vk/AuthorProfileCollector$collectAndRegister$1.L$4 : Ljava/lang/Object;
    ALOAD 22
    ILOAD 1
    PUTFIELD com/example/lomanalyzer/vk/AuthorProfileCollector$collectAndRegister$1.I$0 : I
    ALOAD 22
    ILOAD 6
    PUTFIELD com/example/lomanalyzer/vk/AuthorProfileCollector$collectAndRegister$1.I$1 : I
    ALOAD 22
    ILOAD 7
    PUTFIELD com/example/lomanalyzer/vk/AuthorProfileCollector$collectAndRegister$1.I$2 : I
    ALOAD 22
    ILOAD 10
    PUTFIELD com/example/lomanalyzer/vk/AuthorProfileCollector$collectAndRegister$1.I$3 : I
    ALOAD 22
    ICONST_2
    PUTFIELD com/example/lomanalyzer/vk/AuthorProfileCollector$collectAndRegister$1.label : I
    INVOKESTATIC kotlinx/coroutines/DelayKt.delay (JLkotlin/coroutines/Continuation;)Ljava/lang/Object;
   L150
    DUP
    ALOAD 23
    IF_ACMPNE L151
   L152
    LINENUMBER 59 L152
    ALOAD 23
    ARETURN
   L7
    ALOAD 22
    GETFIELD com/example/lomanalyzer/vk/AuthorProfileCollector$collectAndRegister$1.I$3 : I
    ISTORE 10
    ALOAD 22
    GETFIELD com/example/lomanalyzer/vk/AuthorProfileCollector$collectAndRegister$1.I$2 : I
    ISTORE 7
   L153
    ALOAD 22
    GETFIELD com/example/lomanalyzer/vk/AuthorProfileCollector$collectAndRegister$1.I$1 : I
    ISTORE 6
   L154
    ALOAD 22
    GETFIELD com/example/lomanalyzer/vk/AuthorProfileCollector$collectAndRegister$1.I$0 : I
    ISTORE 1
   L155
    ALOAD 22
    GETFIELD com/example/lomanalyzer/vk/AuthorProfileCollector$collectAndRegister$1.L$4 : Ljava/lang/Object;
    CHECKCAST java/util/Iterator
    ASTORE 9
    ALOAD 22
    GETFIELD com/example/lomanalyzer/vk/AuthorProfileCollector$collectAndRegister$1.L$3 : Ljava/lang/Object;
    CHECKCAST java/util/List
    ASTORE 8
   L156
    ALOAD 22
    GETFIELD com/example/lomanalyzer/vk/AuthorProfileCollector$collectAndRegister$1.L$2 : Ljava/lang/Object;
    CHECKCAST java/util/List
    ASTORE 5
   L157
    ALOAD 22
    GETFIELD com/example/lomanalyzer/vk/AuthorProfileCollector$collectAndRegister$1.L$1 : Ljava/lang/Object;
    CHECKCAST java/lang/String
    ASTORE 2
   L158
    ALOAD 22
    GETFIELD com/example/lomanalyzer/vk/AuthorProfileCollector$collectAndRegister$1.L$0 : Ljava/lang/Object;
    CHECKCAST com/example/lomanalyzer/vk/AuthorProfileCollector
    ASTORE 0
   L159
   L160
    NOP
    ALOAD 21
    INVOKESTATIC kotlin/ResultKt.throwOnFailure (Ljava/lang/Object;)V
    ALOAD 21
   L151
    LINENUMBER 139 L151
    POP
   L161
    GOTO L72
   L73
   L162
   L163
    LINENUMBER 142 L163
    ILOAD 7
    ICONST_0
    IF_ICMPLE L164
   L165
    LINENUMBER 143 L165
    ALOAD 0
    GETFIELD com/example/lomanalyzer/vk/AuthorProfileCollector.sessionEventService : Lcom/example/lomanalyzer/vk/SessionEventService;
   L166
    LINENUMBER 144 L166
    ILOAD 1
   L167
    LINENUMBER 145 L167
    ILOAD 7
    ILOAD 6
    INVOKEDYNAMIC makeConcatWithConstants(II)Ljava/lang/String; [
      // handle kind 0x6 : INVOKESTATIC
      java/lang/invoke/StringConcatFactory.makeConcatWithConstants(Ljava/lang/invoke/MethodHandles$Lookup;Ljava/lang/String;Ljava/lang/invoke/MethodType;Ljava/lang/String;[Ljava/lang/Object;)Ljava/lang/invoke/CallSite;
      // arguments:
      "\u0417\u0430\u043a\u0440\u044b\u0442\u044b\u0435 \u0430\u043a\u043a\u0430\u0443\u043d\u0442\u044b: \u0001 \u0438\u0437 \u0001 (\u0438\u0441\u043a\u043b\u044e\u0447\u0435\u043d\u044b \u0438\u0437 \u043e\u0431\u0440\u0430\u0431\u043e\u0442\u043a\u0438)"
    ]
   L168
    LINENUMBER 143 L168
    ACONST_NULL
    ICONST_4
    ACONST_NULL
    INVOKESTATIC com/example/lomanalyzer/vk/SessionEventService.logInfo$default (Lcom/example/lomanalyzer/vk/SessionEventService;ILjava/lang/String;Ljava/lang/String;ILjava/lang/Object;)V
   L164
   L169
   L170
    LINENUMBER 149 L170
    ALOAD 0
    GETFIELD com/example/lomanalyzer/vk/AuthorProfileCollector.sessionEventService : Lcom/example/lomanalyzer/vk/SessionEventService;
   L171
    LINENUMBER 150 L171
    ILOAD 1
   L172
    LINENUMBER 151 L172
    ILOAD 6
    ILOAD 7
    INVOKEDYNAMIC makeConcatWithConstants(II)Ljava/lang/String; [
      // handle kind 0x6 : INVOKESTATIC
      java/lang/invoke/StringConcatFactory.makeConcatWithConstants(Ljava/lang/invoke/MethodHandles$Lookup;Ljava/lang/String;Ljava/lang/invoke/MethodType;Ljava/lang/String;[Ljava/lang/Object;)Ljava/lang/invoke/CallSite;
      // arguments:
      "\u0420\u0435\u0435\u0441\u0442\u0440 \u0430\u0432\u0442\u043e\u0440\u043e\u0432 \u0437\u0430\u0432\u0435\u0440\u0448\u0451\u043d: \u0001 \u0430\u0432\u0442\u043e\u0440\u043e\u0432 (\u0001 \u0437\u0430\u043a\u0440\u044b\u0442\u044b\u0445)"
    ]
   L173
    LINENUMBER 149 L173
    ACONST_NULL
    ICONST_4
    ACONST_NULL
    INVOKESTATIC com/example/lomanalyzer/vk/SessionEventService.logInfo$default (Lcom/example/lomanalyzer/vk/SessionEventService;ILjava/lang/String;Ljava/lang/String;ILjava/lang/Object;)V
   L174
    LINENUMBER 154 L174
    ILOAD 6
    INVOKESTATIC kotlin/coroutines/jvm/internal/Boxing.boxInt (I)Ljava/lang/Integer;
    ARETURN
   L175
   L176
   L177
   L8
    LINENUMBER 59 L8
    NEW java/lang/IllegalStateException
    DUP
    LDC "call to 'resume' before 'invoke' with coroutine"
    INVOKESPECIAL java/lang/IllegalStateException.<init> (Ljava/lang/String;)V
    ATHROW
    RETURN
   L178
    LOCALVARIABLE this Lcom/example/lomanalyzer/vk/AuthorProfileCollector; L9 L23 0
    LOCALVARIABLE this Lcom/example/lomanalyzer/vk/AuthorProfileCollector; L24 L30 0
    LOCALVARIABLE this Lcom/example/lomanalyzer/vk/AuthorProfileCollector; L31 L45 0
    LOCALVARIABLE this Lcom/example/lomanalyzer/vk/AuthorProfileCollector; L46 L52 0
    LOCALVARIABLE this Lcom/example/lomanalyzer/vk/AuthorProfileCollector; L53 L59 0
    LOCALVARIABLE this Lcom/example/lomanalyzer/vk/AuthorProfileCollector; L60 L6 0
    LOCALVARIABLE this Lcom/example/lomanalyzer/vk/AuthorProfileCollector; L87 L96 0
    LOCALVARIABLE this Lcom/example/lomanalyzer/vk/AuthorProfileCollector; L96 L102 0
    LOCALVARIABLE this Lcom/example/lomanalyzer/vk/AuthorProfileCollector; L102 L7 0
    LOCALVARIABLE this Lcom/example/lomanalyzer/vk/AuthorProfileCollector; L159 L176 0
    LOCALVARIABLE sessionId I L9 L23 1
    LOCALVARIABLE sessionId I L24 L30 1
    LOCALVARIABLE sessionId I L31 L45 1
    LOCALVARIABLE sessionId I L46 L52 1
    LOCALVARIABLE sessionId I L53 L59 1
    LOCALVARIABLE sessionId I L60 L6 1
    LOCALVARIABLE sessionId I L83 L96 1
    LOCALVARIABLE sessionId I L96 L102 1
    LOCALVARIABLE sessionId I L102 L7 1
    LOCALVARIABLE sessionId I L155 L176 1
    LOCALVARIABLE accessToken Ljava/lang/String; L9 L23 2
    LOCALVARIABLE accessToken Ljava/lang/String; L24 L30 2
    LOCALVARIABLE accessToken Ljava/lang/String; L31 L45 2
    LOCALVARIABLE accessToken Ljava/lang/String; L46 L52 2
    LOCALVARIABLE accessToken Ljava/lang/String; L53 L58 2
    LOCALVARIABLE accessToken Ljava/lang/String; L60 L6 2
    LOCALVARIABLE accessToken Ljava/lang/String; L86 L96 2
    LOCALVARIABLE accessToken Ljava/lang/String; L96 L102 2
    LOCALVARIABLE accessToken Ljava/lang/String; L102 L7 2
    LOCALVARIABLE accessToken Ljava/lang/String; L158 L73 2
    LOCALVARIABLE posts Ljava/util/List; L11 L13 4
    LOCALVARIABLE uniqueVkIds Ljava/util/List; L55 L58 5
    LOCALVARIABLE uniqueVkIds Ljava/util/List; L60 L6 5
    LOCALVARIABLE uniqueVkIds Ljava/util/List; L85 L96 5
    LOCALVARIABLE uniqueVkIds Ljava/util/List; L96 L102 5
    LOCALVARIABLE uniqueVkIds Ljava/util/List; L102 L7 5
    LOCALVARIABLE uniqueVkIds Ljava/util/List; L157 L73 5
    LOCALVARIABLE $this$map$iv Ljava/lang/Iterable; L13 L15 6
    LOCALVARIABLE $this$filter$iv Ljava/lang/Iterable; L32 L35 6
    LOCALVARIABLE registered I L64 L6 6
    LOCALVARIABLE registered I L82 L96 6
    LOCALVARIABLE registered I L96 L102 6
    LOCALVARIABLE registered I L102 L7 6
    LOCALVARIABLE registered I L154 L176 6
    LOCALVARIABLE closedCount I L66 L6 7
    LOCALVARIABLE closedCount I L81 L96 7
    LOCALVARIABLE closedCount I L96 L102 7
    LOCALVARIABLE closedCount I L102 L7 7
    LOCALVARIABLE closedCount I L153 L176 7
    LOCALVARIABLE $this$mapTo$iv$iv Ljava/lang/Iterable; L15 L17 8
    LOCALVARIABLE $this$filterTo$iv$iv Ljava/lang/Iterable; L35 L37 8
    LOCALVARIABLE batches Ljava/util/List; L68 L6 8
    LOCALVARIABLE batches Ljava/util/List; L84 L96 8
    LOCALVARIABLE batches Ljava/util/List; L96 L102 8
    LOCALVARIABLE batches Ljava/util/List; L102 L7 8
    LOCALVARIABLE batches Ljava/util/List; L156 L73 8
    LOCALVARIABLE destination$iv$iv Ljava/util/Collection; L15 L27 9
    LOCALVARIABLE destination$iv$iv Ljava/util/Collection; L35 L49 9
    LOCALVARIABLE batchIdx I L74 L6 11
    LOCALVARIABLE batchIdx I L80 L92 11
    LOCALVARIABLE batchIdx I L96 L100 11
    LOCALVARIABLE batchIdx I L102 L146 11
    LOCALVARIABLE item$iv$iv Ljava/lang/Object; L19 L26 12
    LOCALVARIABLE element$iv$iv Ljava/lang/Object; L39 L48 12
    LOCALVARIABLE batch Ljava/util/List; L75 L77 12
    LOCALVARIABLE it Lorg/jetbrains/exposed/sql/ResultRow; L20 L24 13
    LOCALVARIABLE it I L40 L42 13
    LOCALVARIABLE response Lcom/example/lomanalyzer/vk/models/VkResponse; L89 L94 13
    LOCALVARIABLE response Lcom/example/lomanalyzer/vk/models/VkResponse; L96 L99 13
    LOCALVARIABLE users Ljava/util/List; L104 L106 14
    LOCALVARIABLE processed I L139 L143 15
    LOCALVARIABLE user Lcom/example/lomanalyzer/vk/models/VkUser; L109 L131 16
    LOCALVARIABLE existing Lorg/jetbrains/exposed/sql/ResultRow; L111 L113 17
    LOCALVARIABLE authorDbId I L127 L129 18
    LOCALVARIABLE $i$a$-map-AuthorProfileCollector$collectAndRegister$uniqueVkIds$1 I L21 L24 14
    LOCALVARIABLE $i$f$mapTo I L16 L27 10
    LOCALVARIABLE $i$f$map I L14 L31 7
    LOCALVARIABLE $i$a$-filter-AuthorProfileCollector$collectAndRegister$uniqueVkIds$2 I L41 L46 14
    LOCALVARIABLE $i$f$filterTo I L36 L49 10
    LOCALVARIABLE $i$f$filter I L34 L53 7
    LOCALVARIABLE $completion Lkotlin/coroutines/Continuation; L0 L178 3
    LOCALVARIABLE $continuation Lkotlin/coroutines/Continuation; L2 L177 22
    LOCALVARIABLE $result Ljava/lang/Object; L3 L177 21
    MAXSTACK = 11
    MAXLOCALS = 24

File is unknown
The root cause java.lang.OutOfMemoryError was thrown at: java.base/java.util.Arrays.copyOf(Arrays.java:3482)
	at org.jetbrains.kotlin.codegen.TransformationMethodVisitor.visitEnd(TransformationMethodVisitor.kt:89)
	at org.jetbrains.org.objectweb.asm.tree.MethodNode.accept(MethodNode.java:772)
	at org.jetbrains.kotlin.backend.jvm.codegen.CoroutineCodegenKt.acceptWithStateMachine(CoroutineCodegen.kt:76)
	at org.jetbrains.kotlin.backend.jvm.codegen.ClassCodegen.generateMethod(ClassCodegen.kt:440)
	at org.jetbrains.kotlin.backend.jvm.codegen.ClassCodegen.generate(ClassCodegen.kt:168)
	at org.jetbrains.kotlin.backend.jvm.FileCodegen.lower(JvmPhases.kt:39)
	at org.jetbrains.kotlin.backend.common.phaser.PhaseFactoriesKt.createFilePhase$lambda$4(PhaseFactories.kt:71)
	at org.jetbrains.kotlin.backend.common.phaser.PhaseBuildersKt$createSimpleNamedCompilerPhase$1.phaseBody(PhaseBuilders.kt:69)
	at org.jetbrains.kotlin.backend.common.phaser.SimpleNamedCompilerPhase.phaseBody(CompilerPhase.kt:226)
	at org.jetbrains.kotlin.backend.common.phaser.AbstractNamedCompilerPhase.invoke(CompilerPhase.kt:113)
	at org.jetbrains.kotlin.backend.common.phaser.PerformByIrFilePhase.invokeSequential(performByIrFile.kt:62)
	at org.jetbrains.kotlin.backend.common.phaser.PerformByIrFilePhase.invoke(performByIrFile.kt:52)
	at org.jetbrains.kotlin.backend.common.phaser.PerformByIrFilePhase.invoke(performByIrFile.kt:38)
	at org.jetbrains.kotlin.backend.common.phaser.NamedCompilerPhase.phaseBody(CompilerPhase.kt:166)
	at org.jetbrains.kotlin.backend.common.phaser.AbstractNamedCompilerPhase.invoke(CompilerPhase.kt:113)
	at org.jetbrains.kotlin.backend.common.phaser.CompositePhase.invoke(PhaseBuilders.kt:27)
	at org.jetbrains.kotlin.backend.common.phaser.CompositePhase.invoke(PhaseBuilders.kt:14)
	at org.jetbrains.kotlin.backend.common.phaser.NamedCompilerPhase.phaseBody(CompilerPhase.kt:166)
	at org.jetbrains.kotlin.backend.common.phaser.AbstractNamedCompilerPhase.invoke(CompilerPhase.kt:113)
	at org.jetbrains.kotlin.backend.common.phaser.CompilerPhaseKt.invokeToplevel(CompilerPhase.kt:62)
	at org.jetbrains.kotlin.backend.jvm.JvmIrCodegenFactory.invokeCodegen(JvmIrCodegenFactory.kt:371)
	at org.jetbrains.kotlin.codegen.CodegenFactory.generateModule(CodegenFactory.kt:47)
	at org.jetbrains.kotlin.backend.jvm.JvmIrCodegenFactory.generateModuleInFrontendIRMode(JvmIrCodegenFactory.kt:433)
	at org.jetbrains.kotlin.cli.jvm.compiler.pipeline.JvmCompilerPipelineKt.generateCodeFromIr(jvmCompilerPipeline.kt:246)
	at org.jetbrains.kotlin.cli.jvm.compiler.pipeline.JvmCompilerPipelineKt.compileModulesUsingFrontendIrAndLightTree(jvmCompilerPipeline.kt:142)
	at org.jetbrains.kotlin.cli.jvm.K2JVMCompiler.doExecute(K2JVMCompiler.kt:148)
	at org.jetbrains.kotlin.cli.jvm.K2JVMCompiler.doExecute(K2JVMCompiler.kt:43)
	at org.jetbrains.kotlin.cli.common.CLICompiler.execImpl(CLICompiler.kt:103)
	at org.jetbrains.kotlin.cli.common.CLICompiler.execImpl(CLICompiler.kt:49)
	at org.jetbrains.kotlin.cli.common.CLITool.exec(CLITool.kt:101)
	at org.jetbrains.kotlin.incremental.IncrementalJvmCompilerRunner.runCompiler(IncrementalJvmCompilerRunner.kt:464)
	at org.jetbrains.kotlin.incremental.IncrementalJvmCompilerRunner.runCompiler(IncrementalJvmCompilerRunner.kt:73)
	at org.jetbrains.kotlin.incremental.IncrementalCompilerRunner.doCompile(IncrementalCompilerRunner.kt:506)
	at org.jetbrains.kotlin.incremental.IncrementalCompilerRunner.compileImpl(IncrementalCompilerRunner.kt:423)
	at org.jetbrains.kotlin.incremental.IncrementalCompilerRunner.compileNonIncrementally(IncrementalCompilerRunner.kt:301)
	at org.jetbrains.kotlin.incremental.IncrementalCompilerRunner.compile(IncrementalCompilerRunner.kt:129)
	at org.jetbrains.kotlin.daemon.CompileServiceImplBase.execIncrementalCompiler(CompileServiceImpl.kt:675)
	at org.jetbrains.kotlin.daemon.CompileServiceImplBase.access$execIncrementalCompiler(CompileServiceImpl.kt:92)
	at org.jetbrains.kotlin.daemon.CompileServiceImpl.compile(CompileServiceImpl.kt:1660)
	at java.base/jdk.internal.reflect.DirectMethodHandleAccessor.invoke(DirectMethodHandleAccessor.java:103)
	at java.base/java.lang.reflect.Method.invoke(Method.java:580)
	at java.rmi/sun.rmi.server.UnicastServerRef.dispatch(UnicastServerRef.java:360)
	at java.rmi/sun.rmi.transport.Transport$1.run(Transport.java:200)
	at java.rmi/sun.rmi.transport.Transport$1.run(Transport.java:197)
	at java.base/java.security.AccessController.doPrivileged(AccessController.java:714)
	at java.rmi/sun.rmi.transport.Transport.serviceCall(Transport.java:196)
	at java.rmi/sun.rmi.transport.tcp.TCPTransport.handleMessages(TCPTransport.java:598)
	at java.rmi/sun.rmi.transport.tcp.TCPTransport$ConnectionHandler.run0(TCPTransport.java:844)
	at java.rmi/sun.rmi.transport.tcp.TCPTransport$ConnectionHandler.lambda$run$0(TCPTransport.java:721)
	at java.base/java.security.AccessController.doPrivileged(AccessController.java:400)
	at java.rmi/sun.rmi.transport.tcp.TCPTransport$ConnectionHandler.run(TCPTransport.java:720)
	at java.base/java.util.concurrent.ThreadPoolExecutor.runWorker(ThreadPoolExecutor.java:1144)
	at java.base/java.util.concurrent.ThreadPoolExecutor$Worker.run(ThreadPoolExecutor.java:642)
	at java.base/java.lang.Thread.run(Thread.java:1583)
Caused by: java.lang.OutOfMemoryError: GC overhead limit exceeded
	at java.base/java.util.Arrays.copyOf(Arrays.java:3482)
	at java.base/java.util.ArrayList.grow(ArrayList.java:237)
	at java.base/java.util.ArrayList.addAll(ArrayList.java:760)
	at kotlin.collections.CollectionsKt__MutableCollectionsKt.addAll(MutableCollections.kt:114)
	at kotlin.collections.CollectionsKt__IterablesKt.flatten(Iterables.kt:49)
	at org.jetbrains.kotlin.codegen.coroutines.CoroutineTransformerMethodVisitor.writeDebugMetadata(CoroutineTransformerMethodVisitor.kt:391)
	at org.jetbrains.kotlin.codegen.coroutines.CoroutineTransformerMethodVisitor.performTransformations(CoroutineTransformerMethodVisitor.kt:213)
	at org.jetbrains.kotlin.codegen.TransformationMethodVisitor.visitEnd(TransformationMethodVisitor.kt:67)
	at org.jetbrains.org.objectweb.asm.tree.MethodNode.accept(MethodNode.java:772)
	at org.jetbrains.kotlin.backend.jvm.codegen.CoroutineCodegenKt.acceptWithStateMachine(CoroutineCodegen.kt:76)
	at org.jetbrains.kotlin.backend.jvm.codegen.ClassCodegen.generateMethod(ClassCodegen.kt:440)
	at org.jetbrains.kotlin.backend.jvm.codegen.ClassCodegen.generate(ClassCodegen.kt:168)
	at org.jetbrains.kotlin.backend.jvm.FileCodegen.lower(JvmPhases.kt:39)
	at org.jetbrains.kotlin.backend.common.phaser.PhaseFactoriesKt.createFilePhase$lambda$4(PhaseFactories.kt:71)
	at org.jetbrains.kotlin.backend.common.phaser.PhaseFactoriesKt$$Lambda/0x000001bc813572e8.invoke(Unknown Source)
	at org.jetbrains.kotlin.backend.common.phaser.PhaseBuildersKt$createSimpleNamedCompilerPhase$1.phaseBody(PhaseBuilders.kt:69)
	at org.jetbrains.kotlin.backend.common.phaser.SimpleNamedCompilerPhase.phaseBody(CompilerPhase.kt:226)
	at org.jetbrains.kotlin.backend.common.phaser.AbstractNamedCompilerPhase.invoke(CompilerPhase.kt:113)
	at org.jetbrains.kotlin.backend.common.phaser.PerformByIrFilePhase.invokeSequential(performByIrFile.kt:62)
	at org.jetbrains.kotlin.backend.common.phaser.PerformByIrFilePhase.invoke(performByIrFile.kt:52)
	at org.jetbrains.kotlin.backend.common.phaser.PerformByIrFilePhase.invoke(performByIrFile.kt:38)
	at org.jetbrains.kotlin.backend.common.phaser.NamedCompilerPhase.phaseBody(CompilerPhase.kt:166)
	at org.jetbrains.kotlin.backend.common.phaser.AbstractNamedCompilerPhase.invoke(CompilerPhase.kt:113)
	at org.jetbrains.kotlin.backend.common.phaser.CompositePhase.invoke(PhaseBuilders.kt:27)
	at org.jetbrains.kotlin.backend.common.phaser.CompositePhase.invoke(PhaseBuilders.kt:14)
	at org.jetbrains.kotlin.backend.common.phaser.NamedCompilerPhase.phaseBody(CompilerPhase.kt:166)
	at org.jetbrains.kotlin.backend.common.phaser.AbstractNamedCompilerPhase.invoke(CompilerPhase.kt:113)
	at org.jetbrains.kotlin.backend.common.phaser.CompilerPhaseKt.invokeToplevel(CompilerPhase.kt:62)
	at org.jetbrains.kotlin.backend.jvm.JvmIrCodegenFactory.invokeCodegen(JvmIrCodegenFactory.kt:371)
	at org.jetbrains.kotlin.codegen.CodegenFactory.generateModule(CodegenFactory.kt:47)
	at org.jetbrains.kotlin.backend.jvm.JvmIrCodegenFactory.generateModuleInFrontendIRMode(JvmIrCodegenFactory.kt:433)
	at org.jetbrains.kotlin.cli.jvm.compiler.pipeline.JvmCompilerPipelineKt.generateCodeFromIr(jvmCompilerPipeline.kt:246)


